MANIFEST.in
README.md
setup.cfg
setup.py
psnprices/__init__.py
psnprices.egg-info/PKG-INFO
psnprices.egg-info/SOURCES.txt
psnprices.egg-info/dependency_links.txt
psnprices.egg-info/entry_points.txt
psnprices.egg-info/top_level.txt
psnprices/cli/__init__.py
psnprices/cli/psncli.py
psnprices/cli/psndealsmailalert.py
psnprices/cli/psnmailalert.py
psnprices/psn/__init__.py
psnprices/psn/psn.py
psnprices/test/__init__.py
psnprices/test/test_psn.py
psnprices/test/test_psnpricealert.py
psnprices/test/test_utils.py
psnprices/utils/__init__.py
psnprices/utils/utils.py