Metadata-Version: 1.1
Name: psnprices
Version: 1.0
Summary: An interface for the undocumented Sony PlayStation Store PSN Api
Home-page: https://github.com/snipem/psnprices
Author: Matthias Kuech
Author-email: halde@matthias-kuech.de
License: GPL2
Download-URL: https://github.com/snipem/psnprices/archive/1.0.tar.gz
Keywords: playstation,store,prices
Platform: UNKNOWN
